cli_scheduler/__init__.py
cli_scheduler/cli_job.py
cli_scheduler/handler.py
cli_scheduler/constants/__init__.py
cli_scheduler/constants/time_constants.py
cli_scheduler/utils/__init__.py
cli_scheduler/utils/function_utils.py
cli_scheduler/utils/logger_utils.py
cli_scheduler/utils/time_utils.py
python_cli_handler-0.1.1.dist-info/LICENSE
python_cli_handler-0.1.1.dist-info/METADATA
python_cli_handler-0.1.1.dist-info/WHEEL
python_cli_handler-0.1.1.dist-info/top_level.txt
python_cli_handler-0.1.1.dist-info/RECORD
